bmcmanager/__init__.py
bmcmanager/cliff.py
bmcmanager/config.py
bmcmanager/errors.py
bmcmanager/exitcode.py
bmcmanager/logs.py
bmcmanager/nagios.py
bmcmanager/version.py
bmcmanager/commands/__init__.py
bmcmanager/commands/base.py
bmcmanager/commands/disks.py
bmcmanager/commands/firmware.py
bmcmanager/commands/ipmitool.py
bmcmanager/commands/lenovo.py
bmcmanager/commands/netbox.py
bmcmanager/commands/open.py
bmcmanager/commands/power.py
bmcmanager/commands/ram.py
bmcmanager/commands/ipmi/__init__.py
bmcmanager/commands/ipmi/address.py
bmcmanager/commands/ipmi/credentials.py
bmcmanager/commands/ipmi/logs.py
bmcmanager/commands/ipmi/reset.py
bmcmanager/commands/ipmi/sensor.py
bmcmanager/commands/ipmi/ssh.py
bmcmanager/commands/server/__init__.py
bmcmanager/commands/server/autoupdate.py
bmcmanager/commands/server/boot.py
bmcmanager/commands/server/list.py
bmcmanager/commands/server/server.py
bmcmanager/commands/server/status.py
bmcmanager/dcim/__init__.py
bmcmanager/dcim/base.py
bmcmanager/dcim/maas.py
bmcmanager/dcim/netbox.py
bmcmanager/firmwares/__init__.py
bmcmanager/firmwares/base.py
bmcmanager/firmwares/lenovo.py
bmcmanager/interactive/__init__.py
bmcmanager/oob/__init__.py
bmcmanager/oob/base.py
bmcmanager/oob/dell.py
bmcmanager/oob/fujitsu.py
bmcmanager/oob/lenovo.py
bmcmanager/utils/__init__.py
bmcmanager/utils/firmware.py
bmcmanager-1.2.1.dist-info/LICENSE
bmcmanager-1.2.1.dist-info/METADATA
bmcmanager-1.2.1.dist-info/WHEEL
bmcmanager-1.2.1.dist-info/entry_points.txt
bmcmanager-1.2.1.dist-info/pbr.json
bmcmanager-1.2.1.dist-info/top_level.txt
bmcmanager-1.2.1.dist-info/RECORD
