Metadata-Version: 2.1
Name: bmcmanager
Version: 1.2.1
Summary: BMCManager is a tool for bare-metal server management
Home-page: https://github.com/grnet/bmcmanager.git
Author: Aggelos Kolaitis
Author-email: akolaitis@admin.grnet.gr
Classifier: Intended Audience :: System Administrators
Classifier: Programming Language :: Python :: 3
Classifier: Programming Language :: Python :: 3.5
Classifier: Programming Language :: Python :: 3.6
Classifier: Programming Language :: Python :: 3.7
Classifier: Programming Language :: Python :: 3.8
Classifier: License :: OSI Approved :: GNU General Public License v3 (GPLv3)
Classifier: Operating System :: OS Independent
Requires-Python: >= 3.5
License-File: LICENSE
Requires-Dist: beautifulsoup4 (==4.9.3)
Requires-Dist: paramiko (==2.7.1)
Requires-Dist: requests (==2.24.0)
Requires-Dist: cliff (==3.4.0)
Requires-Dist: python-libmaas (==0.6.6)
